charsi/__about__.py
charsi/__init__.py
charsi/__main__.py
charsi/instruction.py
charsi/recipe.py
charsi/strings.py
charsi/utils.py
charsi/commands/__init__.py
charsi/commands/imbue.py
charsi-2.2.0.dist-info/METADATA
charsi-2.2.0.dist-info/WHEEL
charsi-2.2.0.dist-info/entry_points.txt
charsi-2.2.0.dist-info/licenses/LICENSE
charsi-2.2.0.dist-info/RECORD
