Metadata-Version: 2.4
Name: charsi
Version: 2.2.0
Summary: A command-line tool to help game modders build string resources for Diablo II: Resurrected.
Project-URL: homepage, https://github.com/garrett-he/charsi
Project-URL: repository, https://github.com/garrett-he/charsi.git
Project-URL: changelog, https://github.com/garrett-he/charsi/blob/main/CHANGELOG.md
Project-URL: issues, https://github.com/garrett-he/charsi/issues
Author-email: Garrett HE <garrett.he@outlook.com>
License: MIT
License-File: LICENSE
Keywords: diablo2resurrected,game,modding
Requires-Python: <3.14,>=3.10
Requires-Dist: lupa>=2.5
Requires-Dist: pydantic>=2.11.7
Requires-Dist: typer>=0.17.3
